pbm/__init__.py
pbm/__main__.py
pbm/cli.py
pbm/desktop.py
pbm/get_pbm.py
pbm/pbm.py
pbm_root-1.10.dist-info/LICENSE
pbm_root-1.10.dist-info/METADATA
pbm_root-1.10.dist-info/WHEEL
pbm_root-1.10.dist-info/entry_points.txt
pbm_root-1.10.dist-info/top_level.txt
pbm_root-1.10.dist-info/RECORD
